pytest_reorder/__init__.py
pytest_reorder/hook.py
pytest_reorder/reorder.py
pytest_reorder-0.1.1.dist-info/METADATA
pytest_reorder-0.1.1.dist-info/RECORD
pytest_reorder-0.1.1.dist-info/WHEEL
pytest_reorder-0.1.1.dist-info/entry_points.txt
pytest_reorder-0.1.1.dist-info/top_level.txt
