Metadata-Version: 2.1
Name: pytest-reorder
Version: 0.1.1
Summary: Reorder tests depending on their paths and names.
Home-page: https://github.com/not-raspberry/pytest_reorder
Author: not-raspberry
Author-email: unittestablecode@gmail.com
License: MIT
Keywords: pytest order reorder test
Platform: UNKNOWN
Classifier: Development Status :: 4 - Beta
Classifier: Intended Audience :: Developers
Classifier: Topic :: Software Development :: Testing
Classifier: License :: OSI Approved :: MIT License
Classifier: Framework :: Pytest
Classifier: Programming Language :: Python :: 2
Classifier: Programming Language :: Python :: 2.7
Classifier: Programming Language :: Python :: 3
Classifier: Programming Language :: Python :: 3.3
Classifier: Programming Language :: Python :: 3.4
Classifier: Programming Language :: Python :: 3.5
Classifier: Programming Language :: Python :: 3.6
Classifier: Programming Language :: Python :: Implementation :: CPython
Classifier: Programming Language :: Python :: Implementation :: PyPy
Classifier: Operating System :: POSIX :: Linux
Provides-Extra: tests
Requires-Dist: pytest
Provides-Extra: tests
Requires-Dist: pylama (==7.4.3); extra == 'tests'
Requires-Dist: pytest (==3.6.0); extra == 'tests'
Requires-Dist: mock (==2.0.0); extra == 'tests'
